infi.recipe.application_packager-2.0.11-py2.7-nspkg.pth
infi/recipe/application_packager/__init__.py
infi/recipe/application_packager/__version__.py
infi/recipe/application_packager/assertions/__init__.py
infi/recipe/application_packager/auto/__init__.py
infi/recipe/application_packager/base/__init__.py
infi/recipe/application_packager/deb/__init__.py
infi/recipe/application_packager/deb/changelog.in
infi/recipe/application_packager/deb/control.in
infi/recipe/application_packager/deb/md5sums.in
infi/recipe/application_packager/deb/postinst.in
infi/recipe/application_packager/deb/preinst.in
infi/recipe/application_packager/deb/prerm.in
infi/recipe/application_packager/deb/rules.in
infi/recipe/application_packager/installer/__init__.py
infi/recipe/application_packager/msi/__init__.py
infi/recipe/application_packager/msi/silent_launcher-x64.exe
infi/recipe/application_packager/msi/silent_launcher-x86.exe
infi/recipe/application_packager/msi/wix/__init__.py
infi/recipe/application_packager/msi/wix/template.wxs
infi/recipe/application_packager/msi/wix/wixcomponent.inc
infi/recipe/application_packager/msi/wix/wixcondition.inc
infi/recipe/application_packager/msi/wix/wixcustomaction.inc
infi/recipe/application_packager/msi/wix/wixdirectory.inc
infi/recipe/application_packager/msi/wix/wixenvironment.inc
infi/recipe/application_packager/msi/wix/wixfile.inc
infi/recipe/application_packager/msi/wix/wixicon.inc
infi/recipe/application_packager/msi/wix/wixremovefile.inc
infi/recipe/application_packager/msi/wix/wixremovefolder.inc
infi/recipe/application_packager/msi/wix/wixshortcut.inc
infi/recipe/application_packager/msi/wix/wixvariable.inc
infi/recipe/application_packager/pkg/__init__.py
infi/recipe/application_packager/pkg/pkginfo.in
infi/recipe/application_packager/pkg/postinstall.in
infi/recipe/application_packager/pkg/preinstall.in
infi/recipe/application_packager/pkg/preremove.in
infi/recipe/application_packager/rpm/__init__.py
infi.recipe.application_packager-2.0.11.dist-info/LICENSE
infi.recipe.application_packager-2.0.11.dist-info/METADATA
infi.recipe.application_packager-2.0.11.dist-info/WHEEL
infi.recipe.application_packager-2.0.11.dist-info/entry_points.txt
infi.recipe.application_packager-2.0.11.dist-info/namespace_packages.txt
infi.recipe.application_packager-2.0.11.dist-info/top_level.txt
infi.recipe.application_packager-2.0.11.dist-info/RECORD
