Metadata-Version: 2.1
Name: infi.recipe.application-packager
Version: 2.0.11
Summary: buildout recipe for packaging projects as applications
Home-page: https://github.com/Infinidat/infi.recipe.application_packager
Author: Arnon Yaari
Author-email: arnony@infinidat.com
License: BSD
Platform: UNKNOWN
Classifier: Intended Audience :: Developers
Classifier: Intended Audience :: System Administrators
Classifier: License :: OSI Approved :: BSD License
Classifier: Operating System :: OS Independent
Classifier: Programming Language :: Python
Classifier: Programming Language :: Python :: 2
Classifier: Programming Language :: Python :: 3
Classifier: Topic :: Software Development :: Libraries :: Python Modules
Requires-Dist: buildout.wheel (>0.1.2)
Requires-Dist: git-py
Requires-Dist: infi.execute
Requires-Dist: infi.os-info
Requires-Dist: infi.recipe.buildout-logging
Requires-Dist: infi.recipe.close-application
Requires-Dist: infi.recipe.console-scripts
Requires-Dist: infi.registry
Requires-Dist: infi.traceback
Requires-Dist: infi.winver
Requires-Dist: jinja2
Requires-Dist: munch
Requires-Dist: pythonpy
Requires-Dist: setuptools
Requires-Dist: six
Requires-Dist: zc.buildout (>=2.9.2)
